lambdaprompt/__init__.py
lambdaprompt/backends.py
lambdaprompt/gpt3.py
lambdaprompt/prompt.py
lambdaprompt/examples/__init__.py
lambdaprompt/examples/server.py
lambdaprompt/server/__init__.py
lambdaprompt/server/data.py
lambdaprompt/server/main.py
lambdaprompt-0.6.1.dist-info/LICENSE
lambdaprompt-0.6.1.dist-info/METADATA
lambdaprompt-0.6.1.dist-info/WHEEL
lambdaprompt-0.6.1.dist-info/top_level.txt
lambdaprompt-0.6.1.dist-info/RECORD
