Metadata-Version: 2.1
Name: lambdaprompt
Version: 0.6.1
Summary: A functional programming interface for building AI systems
License: MIT
Project-URL: homepage, https://github.com/approximatelabs/lambdaprompt
Keywords: nlp,ai,functional,composition,prompt,apply,chain,machine
Classifier: Programming Language :: Python :: 3
Requires-Python: >=3.7
Provides-Extra: server
Provides-Extra: local
Provides-Extra: all
License-File: LICENSE
